src/__init__.py
src/evolvishub_sqlite_adapter_async/__init__.py
src/evolvishub_sqlite_adapter_async/adapter.py
src/evolvishub_sqlite_adapter_async/config.py
src/evolvishub_sqlite_adapter_async/config_manager.py
src/evolvishub_sqlite_adapter_async/exceptions.py
src/evolvishub_sqlite_adapter_async/logging.py
src/evolvishub_sqlite_adapter_async/type_defs.py
src/evolvishub_sqlite_adapter_async/types.py
evolvishub_sqlite_adapter_async-0.1.1.dist-info/METADATA
evolvishub_sqlite_adapter_async-0.1.1.dist-info/WHEEL
evolvishub_sqlite_adapter_async-0.1.1.dist-info/licenses/LICENSE
evolvishub_sqlite_adapter_async-0.1.1.dist-info/RECORD
