Metadata-Version: 2.4
Name: evolvishub-sqlite-adapter-async
Version: 0.1.1
Summary: A professional async SQLite adapter library
Project-URL: Homepage, https://github.com/evolvisai/evolvishub-sqlite-adapter
Project-URL: Documentation, https://evolvishub-sqlite-adapter.readthedocs.io/
Project-URL: Repository, https://github.com/evolvisai/evolvishub-sqlite-adapter.git
Project-URL: Issues, https://github.com/evolvisai/evolvishub-sqlite-adapter/issues
Author-email: "Alban Maxhuni, PhD" <amaxhuni@evolvis.ai>
License-Expression: MIT
License-File: LICENSE
Keywords: adapter,async,database,sqlite
Classifier: Development Status :: 4 - Beta
Classifier: Framework :: AsyncIO
Classifier: Intended Audience :: Developers
Classifier: License :: OSI Approved :: MIT License
Classifier: Programming Language :: Python :: 3
Classifier: Programming Language :: Python :: 3.9
Classifier: Programming Language :: Python :: 3.10
Classifier: Programming Language :: Python :: 3.11
Classifier: Programming Language :: Python :: 3.12
Classifier: Topic :: Database
Classifier: Topic :: Software Development :: Libraries :: Python Modules
Classifier: Typing :: Typed
Requires-Python: >=3.9
Requires-Dist: aiosqlite>=0.19.0
Requires-Dist: typing-extensions>=4.5.0
Provides-Extra: dev
Requires-Dist: black>=23.1.0; extra == 'dev'
Requires-Dist: build>=1.0.0; extra == 'dev'
Requires-Dist: isort>=5.12.0; extra == 'dev'
Requires-Dist: mypy>=1.0.0; extra == 'dev'
Requires-Dist: pytest-asyncio>=0.21.0; extra == 'dev'
Requires-Dist: pytest-cov>=4.1.0; extra == 'dev'
Requires-Dist: pytest>=7.0.0; extra == 'dev'
Requires-Dist: ruff>=0.1.0; extra == 'dev'
Requires-Dist: wheel>=0.42.0; extra == 'dev'
Provides-Extra: docs
Requires-Dist: sphinx-autodoc-typehints>=1.24.0; extra == 'docs'
Requires-Dist: sphinx-rtd-theme>=1.3.0; extra == 'docs'
Requires-Dist: sphinx>=7.0.0; extra == 'docs'
